settings/__init__.py
settings/debug.py
settings/defaults.py
settings/logging.py
meta3_demo-0.3.0.dist-info/LICENSE
meta3_demo-0.3.0.dist-info/METADATA
meta3_demo-0.3.0.dist-info/WHEEL
meta3_demo-0.3.0.dist-info/top_level.txt
meta3_demo-0.3.0.dist-info/RECORD
